AUTHORS.rst
CHANGELOG.rst
CONTRIBUTING.rst
LICENSE
MANIFEST.in
README.rst
setup.cfg
setup.py
django_filtersmerger/__init__.py
django_filtersmerger/apps.py
django_filtersmerger/filter.py
django_filtersmerger/merger.py
django_filtersmerger/params.py
django_filtersmerger/tests.py
django_filtersmerger/total.py
django_filtersmerger.egg-info/PKG-INFO
django_filtersmerger.egg-info/SOURCES.txt
django_filtersmerger.egg-info/dependency_links.txt
django_filtersmerger.egg-info/requires.txt
django_filtersmerger.egg-info/top_level.txt
django_filtersmerger/templatetags/__init__.py
django_filtersmerger/templatetags/filtersmerger_utils.py